xbox_monitor.py
xbox_monitor-1.8.dist-info/licenses/LICENSE
xbox_monitor-1.8.dist-info/METADATA
xbox_monitor-1.8.dist-info/WHEEL
xbox_monitor-1.8.dist-info/entry_points.txt
xbox_monitor-1.8.dist-info/top_level.txt
xbox_monitor-1.8.dist-info/RECORD
