Metadata-Version: 2.4
Name: xbox_monitor
Version: 1.8
Summary: Tool implementing real-time tracking of Xbox Live players activities
Author-email: Michal Szymanski <misiektoja-pypi@rm-rf.ninja>
License-Expression: GPL-3.0-or-later
Project-URL: Homepage, https://github.com/misiektoja/xbox_monitor
Project-URL: Source, https://github.com/misiektoja/xbox_monitor
Project-URL: Changelog, https://github.com/misiektoja/xbox_monitor/blob/main/RELEASE_NOTES.md
Keywords: xbox,xbox-live,monitoring,tracking,real-time,osint,xbox-webapi
Classifier: Programming Language :: Python :: 3
Classifier: Operating System :: OS Independent
Classifier: Operating System :: Microsoft :: Windows
Classifier: Operating System :: POSIX :: Linux
Classifier: Operating System :: MacOS :: MacOS X
Requires-Python: >=3.8
License-File: LICENSE
Requires-Dist: xbox-webapi>=2.1.0
Requires-Dist: requests>=2.0
Requires-Dist: python-dateutil>=2.8
Requires-Dist: httpx>=0.26.0
Requires-Dist: pytz>=2020.1
Requires-Dist: tzlocal>=4.0
Requires-Dist: python-dotenv>=0.19
Dynamic: license-file
